cjk404/.gitignore
cjk404/__init__.py
cjk404/apps.py
cjk404/middleware.py
cjk404/models.py
cjk404/tests.py
cjk404/testsettings.py
cjk404/wagtail_hooks.py
cjk404/migrations/0001_initial.py
cjk404/migrations/0001_squashed_0006_auto_20211011_2219.py
cjk404/migrations/0002_alter_pagenotfoundentry_id.py
cjk404/migrations/0002_pagenotfoundentry_fallback_redirect.py
cjk404/migrations/0003_alter_pagenotfoundentry_redirect_to_url_and_more.py
cjk404/migrations/0003_pagenotfoundentry_regular_expression.py
cjk404/migrations/0004_alter_pagenotfoundentry_url.py
cjk404/migrations/0004_auto_20210830_1007.py
cjk404/migrations/0005_auto_20211011_2131.py
cjk404/migrations/0006_auto_20211011_2219.py
cjk404/migrations/__init__.py
wagtail_cjk404-24.5.1.dist-info/LICENSE
wagtail_cjk404-24.5.1.dist-info/METADATA
wagtail_cjk404-24.5.1.dist-info/WHEEL
wagtail_cjk404-24.5.1.dist-info/top_level.txt
wagtail_cjk404-24.5.1.dist-info/RECORD
