Metadata-Version: 2.1
Name: wagtail-cjk404
Version: 24.5.1
Summary: 404 handler for Wagtail, with regexp support
Home-page: https://github.com/cjkpl/wagtail-cjk404
Author: Grzegorz Krol, Filip Wozniak
Author-email: Grzegorz Krol <gk@cjk.pl>
License: BSD-3-Clause
Project-URL: Homepage, https://github.com/cjkpl/wagtail-cjk404
Project-URL: Repository, https://github.com/cjkpl/wagtail-cjk404
Keywords: wagtail,django,cms
Classifier: Environment :: Web Environment
Classifier: Framework :: Django
Classifier: Framework :: Wagtail :: 5
Classifier: Framework :: Wagtail :: 6
Classifier: Intended Audience :: Developers
Classifier: License :: OSI Approved :: BSD License
Classifier: Operating System :: OS Independent
Classifier: Programming Language :: Python
Classifier: Programming Language :: Python :: 3
Classifier: Programming Language :: Python :: 3 :: Only
Classifier: Programming Language :: Python :: 3.9
Classifier: Programming Language :: Python :: 3.10
Classifier: Programming Language :: Python :: 3.11
Classifier: Programming Language :: Python :: 3.12
Classifier: Topic :: Internet :: WWW/HTTP
Requires-Python: >=3.9
License-File: LICENSE
Requires-Dist: Wagtail >=4.0.1
Provides-Extra: dev
Requires-Dist: ruff ; extra == 'dev'
Requires-Dist: codespell ; extra == 'dev'
Requires-Dist: build ; extra == 'dev'
